picocog/__init__.py
picocog/picocog.py
picocog-1.0.0.dist-info/LICENSE
picocog-1.0.0.dist-info/METADATA
picocog-1.0.0.dist-info/WHEEL
picocog-1.0.0.dist-info/top_level.txt
picocog-1.0.0.dist-info/RECORD
