Metadata-Version: 2.1
Name: picocog
Version: 1.0.0
Summary: A Python implementation of the picocog library (original Java version by Chris Ainsley)
Home-page: UNKNOWN
License: MIT
Project-URL: Bug Tracker, https://github.com/fontoura/picocog-python/issues
Project-URL: Source Code, https://github.com/fontoura/picocog-python
Keywords: code generation
Platform: UNKNOWN
License-File: LICENSE
